argcast.py
argcast-0.3.0.dist-info/licenses/LICENSE
argcast-0.3.0.dist-info/METADATA
argcast-0.3.0.dist-info/WHEEL
argcast-0.3.0.dist-info/top_level.txt
argcast-0.3.0.dist-info/RECORD
